ZetcodeServletJiaochengChuyiFix1/README.md
ZetcodeServletJiaochengChuyiFix1/__init__.py
ZetcodeServletJiaochengChuyiFix1/__main__.py
ZetcodeServletJiaochengChuyiFix1/file.epub
ZetcodeServletJiaochengChuyiFix1/index.html
ZetcodeServletJiaochengChuyiFix1/css/__init__.py
ZetcodeServletJiaochengChuyiFix1/css/annotations.css
ZetcodeServletJiaochengChuyiFix1/css/main.css
ZetcodeServletJiaochengChuyiFix1/css/normalize.css
ZetcodeServletJiaochengChuyiFix1/css/popup.css
ZetcodeServletJiaochengChuyiFix1/font/__init__.py
ZetcodeServletJiaochengChuyiFix1/font/fontello.eot
ZetcodeServletJiaochengChuyiFix1/font/fontello.svg
ZetcodeServletJiaochengChuyiFix1/font/fontello.ttf
ZetcodeServletJiaochengChuyiFix1/font/fontello.woff
ZetcodeServletJiaochengChuyiFix1/img/__init__.py
ZetcodeServletJiaochengChuyiFix1/img/annotator-glyph-sprite.png
ZetcodeServletJiaochengChuyiFix1/img/annotator-icon-sprite.png
ZetcodeServletJiaochengChuyiFix1/img/apple-touch-icon.png
ZetcodeServletJiaochengChuyiFix1/img/cancelfullscreen.png
ZetcodeServletJiaochengChuyiFix1/img/close.png
ZetcodeServletJiaochengChuyiFix1/img/fullscreen.png
ZetcodeServletJiaochengChuyiFix1/img/loader.gif
ZetcodeServletJiaochengChuyiFix1/img/menu-icon.png
ZetcodeServletJiaochengChuyiFix1/img/save.png
ZetcodeServletJiaochengChuyiFix1/img/saved.png
ZetcodeServletJiaochengChuyiFix1/img/settings-s.png
ZetcodeServletJiaochengChuyiFix1/img/settings.png
ZetcodeServletJiaochengChuyiFix1/img/star.png
ZetcodeServletJiaochengChuyiFix1/js/__init__.py
ZetcodeServletJiaochengChuyiFix1/js/epub.js
ZetcodeServletJiaochengChuyiFix1/js/epub.min.js
ZetcodeServletJiaochengChuyiFix1/js/epub.min.map
ZetcodeServletJiaochengChuyiFix1/js/hooks.min.js
ZetcodeServletJiaochengChuyiFix1/js/hooks.min.map
ZetcodeServletJiaochengChuyiFix1/js/reader.js
ZetcodeServletJiaochengChuyiFix1/js/reader.js.map
ZetcodeServletJiaochengChuyiFix1/js/reader.min.js
ZetcodeServletJiaochengChuyiFix1/js/reader.min.map
ZetcodeServletJiaochengChuyiFix1/js/hooks/__init__.py
zetcode_servlet_jiaocheng_chuyi_fix1-2025.3.24.1.dist-info/METADATA
zetcode_servlet_jiaocheng_chuyi_fix1-2025.3.24.1.dist-info/WHEEL
zetcode_servlet_jiaocheng_chuyi_fix1-2025.3.24.1.dist-info/entry_points.txt
zetcode_servlet_jiaocheng_chuyi_fix1-2025.3.24.1.dist-info/top_level.txt
zetcode_servlet_jiaocheng_chuyi_fix1-2025.3.24.1.dist-info/RECORD
